pyboin/__init__.py
pyboin/pyboin.py
pyboin-0.4.0.dist-info/LICENSE
pyboin-0.4.0.dist-info/METADATA
pyboin-0.4.0.dist-info/WHEEL
pyboin-0.4.0.dist-info/top_level.txt
pyboin-0.4.0.dist-info/RECORD
