Metadata-Version: 2.1
Name: pyboin
Version: 0.4.0
Summary: UNKNOWN
Home-page: https://github.com/AjxLab/pyboin
Author: Tatsuya Abe
Author-email: abe12@mccc.jp
License: MIT
Keywords: japanese romaji hiragana katakana
Platform: UNKNOWN
Classifier: License :: OSI Approved :: MIT License
Classifier: Programming Language :: Python :: 3.7
Requires-Dist: jaconv
